AUTHORS
CHANGELOG
LICENSE
MANIFEST.in
README.rst
buildout.cfg
gulpfile.js
package.json
setup.py
versions.cfg
demo/__init__.py
demo/settings.py
demo/urls.py
django_blog_xinnia.egg-info/PKG-INFO
django_blog_xinnia.egg-info/SOURCES.txt
django_blog_xinnia.egg-info/dependency_links.txt
django_blog_xinnia.egg-info/not-zip-safe
django_blog_xinnia.egg-info/requires.txt
django_blog_xinnia.egg-info/top_level.txt
docs/Makefile
docs/conf.py
docs/index.rst
docs/requirements.txt
docs/development/buildout.rst
docs/development/contribution.rst
docs/development/tests.rst
docs/extensions/__init__.py
docs/extensions/settings.py
docs/extensions/zinnia_docs.py
docs/getting-started/configuration.rst
docs/getting-started/install.rst
docs/getting-started/overview.rst
docs/getting-started/upgrading.rst
docs/how-to/customize_look_and_feel.rst
docs/how-to/extending_entry_model.rst
docs/how-to/rewriting_entry_url.rst
docs/notes/changelog.rst
docs/notes/compatibility.rst
docs/notes/faq.rst
docs/notes/thanks.rst
docs/ref/settings.rst
docs/ref/templatetags.rst
docs/ref/api/zinnia.admin.rst
docs/ref/api/zinnia.models.rst
docs/ref/api/zinnia.models_bases.rst
docs/ref/api/zinnia.rst
docs/ref/api/zinnia.spam_checker.backends.rst
docs/ref/api/zinnia.spam_checker.rst
docs/ref/api/zinnia.url_shortener.backends.rst
docs/ref/api/zinnia.url_shortener.rst
docs/ref/api/zinnia.urls.rst
docs/ref/api/zinnia.views.mixins.rst
docs/ref/api/zinnia.views.rst
docs/ref/api/zinnia.xmlrpc.rst
docs/static/favicon.ico
docs/static/logo.png
docs/topics/channels.rst
docs/topics/ecosystem.rst
docs/topics/permissions.rst
docs/topics/search_engines.rst
docs/topics/spam_checker.rst
docs/topics/url_shortener.rst
zinnia/__init__.py
zinnia/apps.py
zinnia/breadcrumbs.py
zinnia/calendar.py
zinnia/comparison.py
zinnia/context.py
zinnia/context_processors.py
zinnia/converters.py
zinnia/feeds.py
zinnia/flags.py
zinnia/managers.py
zinnia/markups.py
zinnia/moderator.py
zinnia/ping.py
zinnia/preview.py
zinnia/search.py
zinnia/settings.py
zinnia/signals.py
zinnia/sitemaps.py
zinnia/templating.py
zinnia/admin/__init__.py
zinnia/admin/category.py
zinnia/admin/entry.py
zinnia/admin/fields.py
zinnia/admin/filters.py
zinnia/admin/forms.py
zinnia/admin/widgets.py
