Metadata-Version: 2.1
Name: django-blog-xinnia
Version: 0.21.3
Summary: A clear and powerful weblog application powered with Django
Home-page: https://github.com/emencia/django-blog-xinnia
Author: Emencia
Author-email: support@emencia.com
License: BSD License
Keywords: django,blog,weblog,zinnia,post,news
Platform: UNKNOWN
Classifier: Framework :: Django
Classifier: Development Status :: 5 - Production/Stable
Classifier: Environment :: Web Environment
Classifier: Programming Language :: Python :: 3
Classifier: Intended Audience :: Developers
Classifier: Operating System :: OS Independent
Classifier: License :: OSI Approved :: BSD License
Classifier: Topic :: Software Development :: Libraries :: Python Modules
